plottree/__init__.py
plottree/plottree.py
plottree-0.0.2.dist-info/LICENSE
plottree-0.0.2.dist-info/METADATA
plottree-0.0.2.dist-info/WHEEL
plottree-0.0.2.dist-info/entry_points.txt
plottree-0.0.2.dist-info/top_level.txt
plottree-0.0.2.dist-info/RECORD
