Metadata-Version: 2.1
Name: plottree
Version: 0.0.2
Summary: plottree - A command tool for quickly visualizing
Home-page: https://github.com/iBiology/plottree
Author: FEI YUAN
Author-email: yuanfeifuzzy@gmail.com
License: MIT
Keywords: phylogeny tree dendrogram visualization plot bioinformatics
Platform: UNKNOWN
Classifier: Development Status :: 3 - Alpha
Classifier: Environment :: Console
Classifier: Intended Audience :: Developers
Classifier: Intended Audience :: Science/Research
Classifier: License :: OSI Approved :: MIT License
Classifier: Natural Language :: English
Classifier: Programming Language :: Python
Classifier: Topic :: Scientific/Engineering :: Bio-Informatics
Requires-Dist: biopython
Requires-Dist: matplotlib (>=)
